.gitignore
COPYING
MANIFEST.in
README.rst
requirements.txt
setup.py
test-requirements.txt
tox.ini
Tendril.egg-info/PKG-INFO
Tendril.egg-info/SOURCES.txt
Tendril.egg-info/dependency_links.txt
Tendril.egg-info/entry_points.txt
Tendril.egg-info/requires.txt
Tendril.egg-info/top_level.txt
tendril/__init__.py
tendril/application.py
tendril/connection.py
tendril/framers.py
tendril/manager.py
tendril/tcp.py
tendril/udp.py
tendril/utils.py
tests/__init__.py
tests/function/__init__.py
tests/function/base.py
tests/function/test_tcp.py
tests/function/test_udp.py
tests/unit/__init__.py
tests/unit/test_application.py
tests/unit/test_connection.py
tests/unit/test_framers.py
tests/unit/test_manager.py
tests/unit/test_tcp.py
tests/unit/test_udp.py
tests/unit/test_utils.py